ferb/__init__.py
ferb/ferb.py
ferb/ferbCode.py
ferb-1.0.0.dist-info/LICENSE
ferb-1.0.0.dist-info/METADATA
ferb-1.0.0.dist-info/WHEEL
ferb-1.0.0.dist-info/top_level.txt
ferb-1.0.0.dist-info/RECORD
