Metadata-Version: 2.1
Name: ferb
Version: 1.0.0
Summary: Link Checker: A GUI + JS-rendered multithreaded broken link checker for dynamic websites.
Author: Shreyash Srivastva
Author-email: Shreyash Srivastva <usershreyash@gmail.com>
Keywords: broken links,SEO,crawler,GUI,playwright,checker,link checker
Classifier: Programming Language :: Python :: 3
Classifier: Programming Language :: Python :: 3.8
Classifier: License :: OSI Approved :: MIT License
Classifier: Operating System :: OS Independent
Classifier: Development Status :: 4 - Beta
Classifier: Intended Audience :: Developers
Classifier: Topic :: Internet :: WWW/HTTP :: Indexing/Search
Classifier: Topic :: Utilities
Requires-Python: >=3.8
License-File: LICENSE
Requires-Dist: requests
Requires-Dist: beautifulsoup4
Requires-Dist: lxml
Requires-Dist: playwright
Requires-Dist: pillow
Requires-Dist: rich
